setup.py
spigotmc/__init__.py
spigotmc.egg-info/PKG-INFO
spigotmc.egg-info/SOURCES.txt
spigotmc.egg-info/dependency_links.txt
spigotmc.egg-info/top_level.txt